setup.py
ParameterToDict/ParameterToDict.py
ParameterToDict/__init__.py
ParameterToDict.egg-info/PKG-INFO
ParameterToDict.egg-info/SOURCES.txt
ParameterToDict.egg-info/dependency_links.txt
ParameterToDict.egg-info/requires.txt
ParameterToDict.egg-info/top_level.txt
bin/ParameterToDict