Metadata-Version: 1.1
Name: ParameterToDict
Version: 1.4
Summary: Converts parameter to dictionary.
Home-page: UNKNOWN
Author: Suyogya Khanal
Author-email: suyogkhanal4@gmail.com
License: UNKNOWN
Download-URL: https://pypi.python.org/pypi/parametertodict
Platform: UNKNOWN
